ndicts/__init__.py
ndicts/data_dict.py
ndicts/nested_dict.py
ndicts-0.3.0.dist-info/LICENSE
ndicts-0.3.0.dist-info/WHEEL
ndicts-0.3.0.dist-info/METADATA
ndicts-0.3.0.dist-info/RECORD
