Metadata-Version: 2.1
Name: ndicts
Version: 0.3.0
Summary: Class to handle nested dictionaries
Home-page: https://github.com/edd313/ndicts
Keywords: nested,dictionary
Author: Edoardo Cicirello
Author-email: e.cicirello@protonmail.com
Requires-Python: >=3.8,<4.0
Classifier: Programming Language :: Python :: 3
Classifier: Programming Language :: Python :: 3.10
Classifier: Programming Language :: Python :: 3.8
Classifier: Programming Language :: Python :: 3.9
Requires-Dist: more-itertools (>=9.0.0,<10.0.0)
Project-URL: Documentation, https://edd313.github.io/ndicts/
Project-URL: Repository, https://github.com/edd313/ndicts
